Metadata-Version: 2.4
Name: iflow-mcp_kukapay_defi-yields-mcp
Version: 0.1.0
Summary: Add your description here
License-File: LICENSE
Requires-Python: >=3.10
Requires-Dist: httpx>=0.27.0
Requires-Dist: mcp[cli]>=1.6.0
